swagger_client/__init__.py
swagger_client/api_client.py
swagger_client/configuration.py
swagger_client/rest.py
swagger_client/api/__init__.py
swagger_client/api/account_type_api.py
swagger_client/api/active_resource_api.py
swagger_client/api/application_api.py
swagger_client/api/artefact_api.py
swagger_client/api/artefact_version_api.py
swagger_client/api/automation_rule_api.py
swagger_client/api/delta_api.py
swagger_client/api/deployment_api.py
swagger_client/api/driver_definition_api.py
swagger_client/api/environment_api.py
swagger_client/api/environment_type_api.py
swagger_client/api/event_api.py
swagger_client/api/humanitec_public_keys_api.py
swagger_client/api/image_api.py
swagger_client/api/matching_criteria_api.py
swagger_client/api/organization_api.py
swagger_client/api/pipeline_approvals_api.py
swagger_client/api/pipeline_runs_api.py
swagger_client/api/pipelines_api.py
swagger_client/api/public_api.py
swagger_client/api/public_keys_api.py
swagger_client/api/registry_api.py
swagger_client/api/resource_account_api.py
swagger_client/api/resource_definition_api.py
swagger_client/api/resource_provision_api.py
swagger_client/api/resource_type_api.py
swagger_client/api/runtime_info_api.py
swagger_client/api/secret_store_api.py
swagger_client/api/set_api.py
swagger_client/api/token_info_api.py
swagger_client/api/user_invite_api.py
swagger_client/api/user_profile_api.py
swagger_client/api/user_role_api.py
swagger_client/api/value_api.py
swagger_client/api/value_set_version_api.py
swagger_client/api/workload_profile_api.py
swagger_client/models/__init__.py
swagger_client/models/account_creds_request.py
swagger_client/models/account_type_request.py
swagger_client/models/account_type_response.py
swagger_client/models/active_resource_request.py
swagger_client/models/active_resource_response.py
swagger_client/models/add_artefact_version_payload_request.py
swagger_client/models/application_creation_request.py
swagger_client/models/application_request.py
unofficial_humanitec_client-0.1.1.dist-info/METADATA
unofficial_humanitec_client-0.1.1.dist-info/WHEEL
unofficial_humanitec_client-0.1.1.dist-info/top_level.txt
unofficial_humanitec_client-0.1.1.dist-info/RECORD
