Metadata-Version: 2.1
Name: unofficial-humanitec-client
Version: 0.1.1
Summary: Generated Python Client for Humanitec API
Home-page: https://gitlab.com/noordsestern/unofficial-humanitec-client
Author: Markus Stahl
License: EUPL 1.2
Keywords: Swagger,Humanitec API
Requires-Dist: urllib3 >=1.15
Requires-Dist: six >=1.10
Requires-Dist: certifi
Requires-Dist: python-dateutil
